[
  {
    "inputs": [],
    "stateMutability": "nonpayable",
    "type": "constructor"
  },
  {
    "anonymous": false,
    "inputs": [
      {
        "indexed": true,
        "internalType": "uint256",
        "name": "productId",
        "type": "uint256"
      },
      {
        "indexed": true,
        "internalType": "address",
        "name": "from",
        "type": "address"
      },
      {
        "indexed": true,
        "internalType": "address",
        "name": "to",
        "type": "address"
      },
      {
        "indexed": false,
        "internalType": "enum FahadSaleem_SupplyChain.ProductStatus",
        "name": "newStatus",
        "type": "uint8"
      }
    ],
    "name": "OwnershipTransferred",
    "type": "event"
  },
  {
    "anonymous": false,
    "inputs": [
      {
        "indexed": true,
        "internalType": "address",
        "name": "wallet",
        "type": "address"
      },
      {
        "indexed": false,
        "internalType": "enum FahadSaleem_SupplyChain.Role",
        "name": "role",
        "type": "uint8"
      },
      {
        "indexed": false,
        "internalType": "string",
        "name": "name",
        "type": "string"
      }
    ],
    "name": "ParticipantRegistered",
    "type": "event"
  },
  {
    "anonymous": false,
    "inputs": [
      {
        "indexed": true,
        "internalType": "uint256",
        "name": "productId",
        "type": "uint256"
      },
      {
        "indexed": false,
        "internalType": "string",
        "name": "name",
        "type": "string"
      },
      {
        "indexed": false,
        "internalType": "address",
        "name": "manufacturer",
        "type": "address"
      }
    ],
    "name": "ProductRegistered",
    "type": "event"
  },
  {
    "inputs": [
      {
        "internalType": "uint256",
        "name": "",
        "type": "uint256"
      }
    ],
    "name": "allProductIds",
    "outputs": [
      {
        "internalType": "uint256",
        "name": "",
        "type": "uint256"
      }
    ],
    "stateMutability": "view",
    "type": "function"
  },
  {
    "inputs": [
      {
        "internalType": "uint256",
        "name": "_productId",
        "type": "uint256"
      }
    ],
    "name": "confirmDelivery",
    "outputs": [],
    "stateMutability": "nonpayable",
    "type": "function"
  },
  {
    "inputs": [],
    "name": "getAllProductIds",
    "outputs": [
      {
        "internalType": "uint256[]",
        "name": "",
        "type": "uint256[]"
      }
    ],
    "stateMutability": "view",
    "type": "function"
  },
  {
    "inputs": [
      {
        "internalType": "address",
        "name": "_wallet",
        "type": "address"
      }
    ],
    "name": "getParticipant",
    "outputs": [
      {
        "components": [
          {
            "internalType": "address",
            "name": "wallet",
            "type": "address"
          },
          {
            "internalType": "enum FahadSaleem_SupplyChain.Role",
            "name": "role",
            "type": "uint8"
          },
          {
            "internalType": "string",
            "name": "name",
            "type": "string"
          },
          {
            "internalType": "bool",
            "name": "registered",
            "type": "bool"
          }
        ],
        "internalType": "struct FahadSaleem_SupplyChain.Participant",
        "name": "",
        "type": "tuple"
      }
    ],
    "stateMutability": "view",
    "type": "function"
  },
  {
    "inputs": [
      {
        "internalType": "uint256",
        "name": "_productId",
        "type": "uint256"
      }
    ],
    "name": "getProduct",
    "outputs": [
      {
        "components": [
          {
            "internalType": "uint256",
            "name": "id",
            "type": "uint256"
          },
          {
            "internalType": "string",
            "name": "name",
            "type": "string"
          },
          {
            "internalType": "string",
            "name": "description",
            "type": "string"
          },
          {
            "internalType": "address",
            "name": "currentOwner",
            "type": "address"
          },
          {
            "internalType": "enum FahadSaleem_SupplyChain.ProductStatus",
            "name": "status",
            "type": "uint8"
          },
          {
            "internalType": "uint256",
            "name": "createdAt",
            "type": "uint256"
          },
          {
            "internalType": "bool",
            "name": "exists",
            "type": "bool"
          }
        ],
        "internalType": "struct FahadSaleem_SupplyChain.Product",
        "name": "",
        "type": "tuple"
      }
    ],
    "stateMutability": "view",
    "type": "function"
  },
  {
    "inputs": [
      {
        "internalType": "uint256",
        "name": "_productId",
        "type": "uint256"
      }
    ],
    "name": "getProductHistory",
    "outputs": [
      {
        "components": [
          {
            "internalType": "address",
            "name": "actor",
            "type": "address"
          },
          {
            "internalType": "enum FahadSaleem_SupplyChain.Role",
            "name": "actorRole",
            "type": "uint8"
          },
          {
            "internalType": "enum FahadSaleem_SupplyChain.ProductStatus",
            "name": "status",
            "type": "uint8"
          },
          {
            "internalType": "uint256",
            "name": "timestamp",
            "type": "uint256"
          },
          {
            "internalType": "string",
            "name": "note",
            "type": "string"
          }
        ],
        "internalType": "struct FahadSaleem_SupplyChain.HistoryEntry[]",
        "name": "",
        "type": "tuple[]"
      }
    ],
    "stateMutability": "view",
    "type": "function"
  },
  {
    "inputs": [],
    "name": "owner",
    "outputs": [
      {
        "internalType": "address",
        "name": "",
        "type": "address"
      }
    ],
    "stateMutability": "view",
    "type": "function"
  },
  {
    "inputs": [
      {
        "internalType": "address",
        "name": "",
        "type": "address"
      }
    ],
    "name": "participants",
    "outputs": [
      {
        "internalType": "address",
        "name": "wallet",
        "type": "address"
      },
      {
        "internalType": "enum FahadSaleem_SupplyChain.Role",
        "name": "role",
        "type": "uint8"
      },
      {
        "internalType": "string",
        "name": "name",
        "type": "string"
      },
      {
        "internalType": "bool",
        "name": "registered",
        "type": "bool"
      }
    ],
    "stateMutability": "view",
    "type": "function"
  },
  {
    "inputs": [
      {
        "internalType": "uint256",
        "name": "",
        "type": "uint256"
      },
      {
        "internalType": "uint256",
        "name": "",
        "type": "uint256"
      }
    ],
    "name": "productHistory",
    "outputs": [
      {
        "internalType": "address",
        "name": "actor",
        "type": "address"
      },
      {
        "internalType": "enum FahadSaleem_SupplyChain.Role",
        "name": "actorRole",
        "type": "uint8"
      },
      {
        "internalType": "enum FahadSaleem_SupplyChain.ProductStatus",
        "name": "status",
        "type": "uint8"
      },
      {
        "internalType": "uint256",
        "name": "timestamp",
        "type": "uint256"
      },
      {
        "internalType": "string",
        "name": "note",
        "type": "string"
      }
    ],
    "stateMutability": "view",
    "type": "function"
  },
  {
    "inputs": [
      {
        "internalType": "uint256",
        "name": "",
        "type": "uint256"
      }
    ],
    "name": "products",
    "outputs": [
      {
        "internalType": "uint256",
        "name": "id",
        "type": "uint256"
      },
      {
        "internalType": "string",
        "name": "name",
        "type": "string"
      },
      {
        "internalType": "string",
        "name": "description",
        "type": "string"
      },
      {
        "internalType": "address",
        "name": "currentOwner",
        "type": "address"
      },
      {
        "internalType": "enum FahadSaleem_SupplyChain.ProductStatus",
        "name": "status",
        "type": "uint8"
      },
      {
        "internalType": "uint256",
        "name": "createdAt",
        "type": "uint256"
      },
      {
        "internalType": "bool",
        "name": "exists",
        "type": "bool"
      }
    ],
    "stateMutability": "view",
    "type": "function"
  },
  {
    "inputs": [
      {
        "internalType": "uint256",
        "name": "_productId",
        "type": "uint256"
      }
    ],
    "name": "receiveFromDistributor",
    "outputs": [],
    "stateMutability": "nonpayable",
    "type": "function"
  },
  {
    "inputs": [
      {
        "internalType": "uint256",
        "name": "_productId",
        "type": "uint256"
      }
    ],
    "name": "receiveFromManufacturer",
    "outputs": [],
    "stateMutability": "nonpayable",
    "type": "function"
  },
  {
    "inputs": [
      {
        "internalType": "address",
        "name": "_wallet",
        "type": "address"
      },
      {
        "internalType": "enum FahadSaleem_SupplyChain.Role",
        "name": "_role",
        "type": "uint8"
      },
      {
        "internalType": "string",
        "name": "_name",
        "type": "string"
      }
    ],
    "name": "registerParticipant",
    "outputs": [],
    "stateMutability": "nonpayable",
    "type": "function"
  },
  {
    "inputs": [
      {
        "internalType": "string",
        "name": "_name",
        "type": "string"
      },
      {
        "internalType": "string",
        "name": "_description",
        "type": "string"
      }
    ],
    "name": "registerProduct",
    "outputs": [
      {
        "internalType": "uint256",
        "name": "",
        "type": "uint256"
      }
    ],
    "stateMutability": "nonpayable",
    "type": "function"
  },
  {
    "inputs": [
      {
        "internalType": "uint256",
        "name": "_productId",
        "type": "uint256"
      },
      {
        "internalType": "address",
        "name": "_customer",
        "type": "address"
      }
    ],
    "name": "sellToCustomer",
    "outputs": [],
    "stateMutability": "nonpayable",
    "type": "function"
  },
  {
    "inputs": [
      {
        "internalType": "uint256",
        "name": "_productId",
        "type": "uint256"
      },
      {
        "internalType": "address",
        "name": "_distributor",
        "type": "address"
      }
    ],
    "name": "shipToDistributor",
    "outputs": [],
    "stateMutability": "nonpayable",
    "type": "function"
  },
  {
    "inputs": [
      {
        "internalType": "uint256",
        "name": "_productId",
        "type": "uint256"
      },
      {
        "internalType": "address",
        "name": "_retailer",
        "type": "address"
      }
    ],
    "name": "shipToRetailer",
    "outputs": [],
    "stateMutability": "nonpayable",
    "type": "function"
  },
  {
    "inputs": [],
    "name": "totalProducts",
    "outputs": [
      {
        "internalType": "uint256",
        "name": "",
        "type": "uint256"
      }
    ],
    "stateMutability": "view",
    "type": "function"
  }
]